LICENSE
README.md
setup.cfg
setup.py
retro_transformer/__init__.py
retro_transformer/bert.py
retro_transformer/model.py
retro_transformer.egg-info/PKG-INFO
retro_transformer.egg-info/SOURCES.txt
retro_transformer.egg-info/dependency_links.txt
retro_transformer.egg-info/requires.txt
retro_transformer.egg-info/top_level.txt
retro_transformer/tools/__init__.py
retro_transformer/tools/database.py
retro_transformer/tools/dataset.py
retro_transformer/tools/optimizer.py
retro_transformer/tools/train.py