Metadata-Version: 2.1
Name: retro-transformer
Version: 1.0.2
Summary: Easy-to-use Retrieval-Enhanced Transformer (Retro) implementation
Home-page: https://github.com/0x7o/RETRO-transformer
Author: Danil Kononyuk
Author-email: me@0x7o.link
License: UNKNOWN
Platform: UNKNOWN
Requires-Python: >=3.6
License-File: LICENSE
